{
  "pageCount": 1,
  "items": [
    {
      "text": "７月６日（月）",
      "page": 1,
      "x": 109.1,
      "y": 689.86,
      "width": 62.55359999999997,
      "height": 11.52
    },
    {
      "text": "７日（火）",
      "page": 1,
      "x": 215.21,
      "y": 689.86,
      "width": 42.90047999999998,
      "height": 11.52
    },
    {
      "text": "８日（水）",
      "page": 1,
      "x": 311.47,
      "y": 689.86,
      "width": 42.90048000000001,
      "height": 11.52
    },
    {
      "text": "９日（木）",
      "page": 1,
      "x": 407.71,
      "y": 689.86,
      "width": 42.90048000000001,
      "height": 11.52
    },
    {
      "text": "１０（金）",
      "page": 1,
      "x": 502.06,
      "y": 689.86,
      "width": 39.30624000000014,
      "height": 11.52
    },
    {
      "text": "陳さんの",
      "page": 1,
      "x": 412.27,
      "y": 656.74,
      "width": 33.803999999999974,
      "height": 9
    },
    {
      "text": "タコライス",
      "page": 1,
      "x": 116.54,
      "y": 642.58,
      "width": 47.784959999999984,
      "height": 11.52
    },
    {
      "text": "旨辛チキン丼",
      "page": 1,
      "x": 203.42,
      "y": 642.58,
      "width": 66.53951999999995,
      "height": 11.52
    },
    {
      "text": "鶏肉飯風",
      "page": 1,
      "x": 309.77,
      "y": 642.58,
      "width": 46.44000000000001,
      "height": 11.52
    },
    {
      "text": "青椒肉絲丼",
      "page": 1,
      "x": 400.15,
      "y": 642.58,
      "width": 58.08000000000001,
      "height": 11.52
    },
    {
      "text": "ハッシュドビーフ",
      "page": 1,
      "x": 482.26,
      "y": 642.58,
      "width": 78.91200000000003,
      "height": 11.52
    },
    {
      "text": "¥350",
      "page": 1,
      "x": 124.7,
      "y": 609.7,
      "width": 31.36439999999999,
      "height": 14.76
    },
    {
      "text": "¥400",
      "page": 1,
      "x": 220.97,
      "y": 609.7,
      "width": 31.36439999999999,
      "height": 14.76
    },
    {
      "text": "¥350",
      "page": 1,
      "x": 317.23,
      "y": 609.7,
      "width": 31.364400000000074,
      "height": 14.76
    },
    {
      "text": "¥350",
      "page": 1,
      "x": 413.5,
      "y": 609.7,
      "width": 31.364400000000074,
      "height": 14.76
    },
    {
      "text": "¥400",
      "page": 1,
      "x": 506.02,
      "y": 609.7,
      "width": 31.364400000000074,
      "height": 14.76
    },
    {
      "text": "スティックフライド",
      "page": 1,
      "x": 480.22,
      "y": 578.74,
      "width": 83.04768000000003,
      "height": 11.52
    },
    {
      "text": "ササミチーズ",
      "page": 1,
      "x": 108.5,
      "y": 562.66,
      "width": 63.85535999999998,
      "height": 11.52
    },
    {
      "text": "キーマカレー",
      "page": 1,
      "x": 204.98,
      "y": 562.66,
      "width": 63.46367999999999,
      "height": 11.52
    },
    {
      "text": "ケイジャンチキン",
      "page": 1,
      "x": 292.01,
      "y": 562.66,
      "width": 81.86112,
      "height": 11.52
    },
    {
      "text": "牛すじ",
      "page": 1,
      "x": 413.38,
      "y": 562.66,
      "width": 31.59936000000001,
      "height": 11.52
    },
    {
      "text": "チキン",
      "page": 1,
      "x": 505.9,
      "y": 562.66,
      "width": 31.64544000000001,
      "height": 11.52
    },
    {
      "text": "¥350",
      "page": 1,
      "x": 124.7,
      "y": 529.27,
      "width": 31.36439999999999,
      "height": 14.76
    },
    {
      "text": "¥350",
      "page": 1,
      "x": 220.97,
      "y": 529.27,
      "width": 31.36439999999999,
      "height": 14.76
    },
    {
      "text": "¥350",
      "page": 1,
      "x": 317.23,
      "y": 529.27,
      "width": 31.364400000000074,
      "height": 14.76
    },
    {
      "text": "¥400",
      "page": 1,
      "x": 413.5,
      "y": 529.27,
      "width": 31.364400000000074,
      "height": 14.76
    },
    {
      "text": "¥350",
      "page": 1,
      "x": 506.02,
      "y": 529.27,
      "width": 31.364400000000074,
      "height": 14.76
    },
    {
      "text": "ナポリタン",
      "page": 1,
      "x": 115.58,
      "y": 482.23,
      "width": 49.73183999999998,
      "height": 11.52
    },
    {
      "text": "トマトクリーム",
      "page": 1,
      "x": 203.54,
      "y": 482.23,
      "width": 66.13631999999998,
      "height": 11.52
    },
    {
      "text": "カルボナーラ",
      "page": 1,
      "x": 301.01,
      "y": 482.23,
      "width": 63.74015999999998,
      "height": 11.52
    },
    {
      "text": "和風クリーム",
      "page": 1,
      "x": 397.27,
      "y": 482.23,
      "width": 63.740160000000024,
      "height": 11.52
    },
    {
      "text": "塩豚チーズ",
      "page": 1,
      "x": 493.66,
      "y": 482.23,
      "width": 56.06784000000006,
      "height": 11.52
    },
    {
      "text": "¥350",
      "page": 1,
      "x": 124.7,
      "y": 448.87,
      "width": 31.36439999999999,
      "height": 14.76
    },
    {
      "text": "¥350",
      "page": 1,
      "x": 220.97,
      "y": 448.87,
      "width": 31.36439999999999,
      "height": 14.76
    },
    {
      "text": "¥350",
      "page": 1,
      "x": 317.23,
      "y": 448.87,
      "width": 31.364400000000074,
      "height": 14.76
    },
    {
      "text": "¥400",
      "page": 1,
      "x": 413.5,
      "y": 448.87,
      "width": 31.364400000000074,
      "height": 14.76
    },
    {
      "text": "¥350",
      "page": 1,
      "x": 506.02,
      "y": 448.87,
      "width": 31.364400000000074,
      "height": 14.76
    },
    {
      "text": "２階食堂",
      "page": 1,
      "x": 241.25,
      "y": 720.7,
      "width": 107.6004,
      "height": 29.52
    },
    {
      "text": "Menu",
      "page": 1,
      "x": 348.82,
      "y": 720.7,
      "width": 64.47167999999999,
      "height": 29.52
    },
    {
      "text": "丼",
      "page": 1,
      "x": 39.288,
      "y": 614.3,
      "width": 44.28,
      "height": 44.28
    },
    {
      "text": "カレー",
      "page": 1,
      "x": 21.552,
      "y": 561.48,
      "width": 78.75936,
      "height": 29.52
    },
    {
      "text": "パスタ",
      "page": 1,
      "x": 19.896,
      "y": 482.57,
      "width": 80.94384,
      "height": 29.52
    },
    {
      "text": "小鉢",
      "page": 1,
      "x": 28.92,
      "y": 401.74,
      "width": 59.04,
      "height": 29.52
    },
    {
      "text": "営業時間",
      "page": 1,
      "x": 255.1,
      "y": 232.8,
      "width": 118.104,
      "height": 29.544
    },
    {
      "text": "２Ｆ食堂",
      "page": 1,
      "x": 141.38,
      "y": 189.29,
      "width": 96.73704,
      "height": 29.52
    },
    {
      "text": "１０：３０～１４：００",
      "page": 1,
      "x": 257.71,
      "y": 189.29,
      "width": 214.9535999999999,
      "height": 29.52
    },
    {
      "text": "土曜日休業",
      "page": 1,
      "x": 225.7,
      "y": 131.3,
      "width": 147.6,
      "height": 29.52
    },
    {
      "text": "都合によりメニューは変更することがあります",
      "page": 1,
      "x": 407.81,
      "y": 702.89,
      "width": 155.4316800000001,
      "height": 8.16
    },
    {
      "text": "ライス￥",
      "page": 1,
      "x": 98.232,
      "y": 409.51,
      "width": 105.79968000000001,
      "height": 29.52
    },
    {
      "text": "100",
      "page": 1,
      "x": 204.05,
      "y": 409.51,
      "width": 48.09336000000003,
      "height": 29.52
    },
    {
      "text": "きんぴら￥",
      "page": 1,
      "x": 271.66,
      "y": 409.51,
      "width": 136.02815999999999,
      "height": 29.52
    },
    {
      "text": "50",
      "page": 1,
      "x": 407.69,
      "y": 409.51,
      "width": 32.061359999999986,
      "height": 29.52
    },
    {
      "text": "ポテト￥",
      "page": 1,
      "x": 459.36,
      "y": 409.51,
      "width": 103.55615999999999,
      "height": 29.52
    },
    {
      "text": "100",
      "page": 1,
      "x": 562.99,
      "y": 409.51,
      "width": 48.141280000000066,
      "height": 29.52
    },
    {
      "text": "ライス（小）￥",
      "page": 1,
      "x": 60.36,
      "y": 371.14,
      "width": 164.78064,
      "height": 29.52
    },
    {
      "text": "50",
      "page": 1,
      "x": 225.22,
      "y": 371.14,
      "width": 32.061360000000015,
      "height": 29.52
    },
    {
      "text": "ミニサラダ￥",
      "page": 1,
      "x": 276.89,
      "y": 371.14,
      "width": 159.7032,
      "height": 29.52
    },
    {
      "text": "50",
      "page": 1,
      "x": 436.63,
      "y": 371.14,
      "width": 32.061359999999986,
      "height": 29.52
    },
    {
      "text": "コロッケ￥",
      "page": 1,
      "x": 488.3,
      "y": 371.14,
      "width": 128.58912,
      "height": 29.52
    },
    {
      "text": "ホームパン￥",
      "page": 1,
      "x": 136.34,
      "y": 332.76,
      "width": 171.12744,
      "height": 29.52
    },
    {
      "text": "120",
      "page": 1,
      "x": 307.49,
      "y": 332.76,
      "width": 48.14127999999995,
      "height": 29.52
    },
    {
      "text": "スイーツ￥",
      "page": 1,
      "x": 375.31,
      "y": 332.76,
      "width": 136.05768,
      "height": 29.52
    },
    {
      "text": "50",
      "page": 1,
      "x": 511.42,
      "y": 332.76,
      "width": 32.08532000000003,
      "height": 29.52
    },
    {
      "text": "～",
      "page": 1,
      "x": 543.5,
      "y": 332.76,
      "width": 29.52,
      "height": 29.52
    }
  ],
  "warnings": []
}
